{"GlobalPropertiesHash":"k92+GQaVRceGVI5+Hxj0tZRcKrfrsKdLp0qAuUCMMIw=","FingerprintPatternsHash":"gq3WsqcKBUGTSNle7RKKyXRIwh7M8ccEqOqYvIzoM04=","PropertyOverridesHash":"8ZRc1sGeVrPBx4lD717BgRaQekyh78QKV9SKsdt638U=","InputHashes":["mOa2eHxHnFxyay4MLiPj6zLmkdf73B4OEwf3YzcdS0s=","rU8YbtP7XlGo8FWHoAPD9nzzWMVw5oOVVaUyijDHWY4=","kCvNbe2gLOl0ysvTtAytrT6fvwyxiJ8kAH2ByInqmwU=","jUzKluOQCLbFlwsmIqUnxoBy0L/DHMull5/lkzee3pA=","Er2u/S7bSDKOrqlDL2FSbC\u002BX\u002BHOp9FVHMroLSiKXQUw=","WlsAeXC7gukS90sc9WvrSSHC1pIjKILJdqY2REVYWdQ=","WmD/9jFqEOy8QyZ03NByrmIrmvCbxYrvDiGJCk/dHQk=","7DQe16TXgRA6NstCpFr2Aqu8csMDK4u\u002BzSkKMbTfUxk=","Hn/cRpO0GgHO14ejw/NnufjD75LwSVbQvIEBNTfzUOc=","XnLdnw1nGo\u002BawyX4Nu4xWdpfV\u002B5lnmk82vBwjZtdPkM=","o4AOWSSg3m4z7reYvKe1bm4CKL\u002BI01L\u002BkfIMehF1UIM=","cbxFV8tSNKqKw7BM1yF9L84fzglOGp5W0NusIK/K83E=","bVSebHSiLTdVyv\u002Bn1phf\u002ByTe3LCtlJlqV6cZ\u002B5SMKic=","s3FNKGl5vy9v8nZRybFkiYueT4xsjXfqB3u2G0PaoO4="],"CachedAssets":{"mOa2eHxHnFxyay4MLiPj6zLmkdf73B4OEwf3YzcdS0s=":{"Identity":"D:\\C#\\Restaurant\\v1.0\\wwwroot\\css\\app.css","SourceId":"VinhKhanhstreetfoods","SourceType":"Discovered","ContentRoot":"D:\\C#\\Restaurant\\v1.0\\wwwroot\\","BasePath":"/","RelativePath":"css/app#[.{fingerprint}]?.css","AssetKind":"All","AssetMode":"All","AssetRole":"Primary","AssetMergeBehavior":null,"AssetMergeSource":"","RelatedAsset":null,"AssetTraitName":null,"AssetTraitValue":null,"Fingerprint":"e5tk7yf482","Integrity":"bhCZyC/yM2\u002BDaFXr8z25\u002B5MeWfXWqMJNNA4ZLAXbjjU=","CopyToOutputDirectory":"Never","CopyToPublishDirectory":"PreserveNewest","OriginalItemSpec":"wwwroot\\css\\app.css","FileLength":3376,"LastWriteTime":"2026-03-13T07:54:51.1515895+00:00"},"rU8YbtP7XlGo8FWHoAPD9nzzWMVw5oOVVaUyijDHWY4=":{"Identity":"D:\\C#\\Restaurant\\v1.0\\wwwroot\\css\\bootstrap\\bootstrap.min.css","SourceId":"VinhKhanhstreetfoods","SourceType":"Discovered","ContentRoot":"D:\\C#\\Restaurant\\v1.0\\wwwroot\\","BasePath":"/","RelativePath":"css/bootstrap/bootstrap.min#[.{fingerprint}]?.css","AssetKind":"All","AssetMode":"All","AssetRole":"Primary","AssetMergeBehavior":null,"AssetMergeSource":"","RelatedAsset":null,"AssetTraitName":null,"AssetTraitValue":null,"Fingerprint":"6gzpyzhau4","Integrity":"SiIVMGgRhdXjKSTIddX7mh9IbOXVcwQWc7/p4nS6D/0=","CopyToOutputDirectory":"Never","CopyToPublishDirectory":"PreserveNewest","OriginalItemSpec":"wwwroot\\css\\bootstrap\\bootstrap.min.css","FileLength":162726,"LastWriteTime":"2026-03-13T07:54:51.1525905+00:00"},"kCvNbe2gLOl0ysvTtAytrT6fvwyxiJ8kAH2ByInqmwU=":{"Identity":"D:\\C#\\Restaurant\\v1.0\\wwwroot\\css\\bootstrap\\bootstrap.min.css.map","SourceId":"VinhKhanhstreetfoods","SourceType":"Discovered","ContentRoot":"D:\\C#\\Restaurant\\v1.0\\wwwroot\\","BasePath":"/","RelativePath":"css/bootstrap/bootstrap.min.css#[.{fingerprint}]?.map","AssetKind":"All","AssetMode":"All","AssetRole":"Primary","AssetMergeBehavior":null,"AssetMergeSource":"","RelatedAsset":null,"AssetTraitName":null,"AssetTraitValue":null,"Fingerprint":"8inm30yfxf","Integrity":"gBwg2tmA0Ci2u54gMF1jNCVku6vznarkLS6D76htNNQ=","CopyToOutputDirectory":"Never","CopyToPublishDirectory":"PreserveNewest","OriginalItemSpec":"wwwroot\\css\\bootstrap\\bootstrap.min.css.map","FileLength":449111,"LastWriteTime":"2026-03-13T07:54:51.1550985+00:00"},"jUzKluOQCLbFlwsmIqUnxoBy0L/DHMull5/lkzee3pA=":{"Identity":"D:\\C#\\Restaurant\\v1.0\\wwwroot\\index.html","SourceId":"VinhKhanhstreetfoods","SourceType":"Discovered","ContentRoot":"D:\\C#\\Restaurant\\v1.0\\wwwroot\\","BasePath":"/","RelativePath":"index#[.{fingerprint}]?.html","AssetKind":"All","AssetMode":"All","AssetRole":"Primary","AssetMergeBehavior":null,"AssetMergeSource":"","RelatedAsset":null,"AssetTraitName":null,"AssetTraitValue":null,"Fingerprint":"d6syom0js5","Integrity":"20wXhMPnn/fOcE8sIrxOEsJ0yxAkqMwl0NSE3fKp9JM=","CopyToOutputDirectory":"Never","CopyToPublishDirectory":"PreserveNewest","OriginalItemSpec":"wwwroot\\index.html","FileLength":873,"LastWriteTime":"2026-03-13T07:54:51.1556355+00:00"}},"CachedCopyCandidates":{}}